structured_markdown/__init__.py
structured_markdown/engine.py
structured_markdown/library.py
structured_markdown-0.2.0.dist-info/LICENSE
structured_markdown-0.2.0.dist-info/METADATA
structured_markdown-0.2.0.dist-info/WHEEL
structured_markdown-0.2.0.dist-info/top_level.txt
structured_markdown-0.2.0.dist-info/RECORD
