Metadata-Version: 2.1
Name: structured-markdown
Version: 0.2.0
Summary: Add an extra dimension to your markdown documents
Home-page: https://github.com/Structured-Markdown/structured_markdown
Author: Structured-Markdown
Author-email: isaacimagine@gmail.com
License: MIT
Platform: UNKNOWN
Classifier: Development Status :: 3 - Alpha
Classifier: License :: OSI Approved :: MIT License
Classifier: Intended Audience :: Developers
Classifier: Programming Language :: Python :: 3.7
Classifier: Topic :: Text Processing :: Markup
Requires-Dist: mistune
Requires-Dist: m2r
